hello_library/__init__.py
hello_library/hello.py
hello_library-0.0.0.dist-info/METADATA
hello_library-0.0.0.dist-info/WHEEL
hello_library-0.0.0.dist-info/top_level.txt
hello_library-0.0.0.dist-info/RECORD
