Metadata-Version: 2.4
Name: hello_library
Version: 0.0.0
Summary: A simple library that prints Lumelang ke Maqai!
Home-page: https://github.com/your_username/hello_library
Author: Sechaba Maqai
Author-email: sechaba.maqai@gmail.com
Classifier: Programming Language :: Python :: 3
Classifier: License :: OSI Approved :: MIT License
Classifier: Operating System :: OS Independent
Requires-Python: >=3.6
Dynamic: author
Dynamic: author-email
Dynamic: classifier
Dynamic: home-page
Dynamic: requires-python
Dynamic: summary
